{"title":"Bağırsak Hastalıkları","meta":{"updatedAt":"16 Mar 2026","tags":["Gastroenteroloji","İshal","Kolon","Malabsorbsiyon","İBH"],"order":3},"sections":[{"heading":"🤖","html":"<p><em>⚠️ <strong>Uyarı:</strong> MediSea</em></p>"},{"heading":"Gastrointestinal Kanalın Dinamikleri","html":"<p>Yaklaşık 6 metre uzunluğundaki ince bağırsak (duodenum, jejunum, ileum) vücudun ana emilim merkezidir. Geriye kalan kalın bağırsak (kolon) ise su ve elektrolit emilimini tamamlayarak dışkıyı şekillendirir. Bu muazzam sistemin herhangi bir noktasındaki fonksiyon bozukluğu, klinik olarak en sık <strong>İshal (Diyare)</strong>, kabızlık veya karın ağrısı ile karşımıza çıkar.</p>"},{"heading":"Hastalık Spektrumu","html":"<p>Bu gruptaki hastalıklar, patofizyolojilerine göre geniş bir yelpazeye ayrılır:</p><ul class=\"mb-4\"><li><strong>Malabsorbsiyon Sendromları:</strong> Bağırsak mukozasının hasar gördüğü veya emilim yüzeyinin azaldığı hastalıklardır. <em>Çölyak Hastalığı</em> (Gluten duyarlılığı) ve <em>Kısa Bağırsak Sendromu</em> bu grubun en klasik örnekleridir. Steatore (yağlı dışkı) ve besin eksiklikleri (anemi, osteoporoz) ile seyrederler.</li><li><strong>İnflamatuar Bağırsak Hastalıkları (İBH):</strong> İmmün sistemin bağırsak florasına karşı verdiği anormal yanıt sonucu gelişen <em>Ülseratif Kolit</em> ve <em>Crohn Hastalığını</em> kapsar. Kronik kanlı ishal, fistüller ve ekstraintestinal bulgular (artrit, üveit) tipiktir.</li><li><strong>Fonksiyonel Bozukluklar:</strong> Hiçbir organik veya biyokimyasal hasar olmaksızın, beyin-bağırsak aksının bozulmasıyla ortaya çıkan <em>İrritabl Bağırsak Sendromu (İBS)</em> bu gruptadır.</li><li><strong>Neoplastik Hastalıklar:</strong> Kolon polipleri ve tüm dünyada en sık görülen ölümcül kanserlerden biri olan Kolorektal Kanserler.</li></ul>"}]}